README.md
setup.py
tokko_es_query_factory/__init__.py
tokko_es_query_factory/exceptions.py
tokko_es_query_factory/filters.py
tokko_es_query_factory/query_factory.py
tokko_es_query_factory.egg-info/PKG-INFO
tokko_es_query_factory.egg-info/SOURCES.txt
tokko_es_query_factory.egg-info/dependency_links.txt
tokko_es_query_factory.egg-info/requires.txt
tokko_es_query_factory.egg-info/top_level.txt