Metadata-Version: 2.1
Name: tokko-es-query-factory
Version: 0.0.2
Summary: Elasticsearch Query Factory
Home-page: https://github.com/TokkoLabs/services-tokkobroker/libraries/tokko_es_query_factory
Author: Navent
Author-email: develper@navent.com
License: BSD License
Platform: UNKNOWN
Classifier: Environment :: Web Environment
Classifier: Intended Audience :: Developers
Classifier: License :: OSI Approved :: BSD License
Classifier: Operating System :: OS Independent
Classifier: Programming Language :: Python
Classifier: Programming Language :: Python :: 3.8
Classifier: Topic :: Internet :: WWW/HTTP
Classifier: Topic :: Internet :: WWW/HTTP :: Dynamic Content
